CMakeLists.txt
LICENSE
MANIFEST.in
README.md
config.cmake
pyproject.toml
requirements.txt
setup.py
cmake/cuda.cmake
deps/cutlass/.git
deps/cutlass/.gitignore
deps/cutlass/.gitmodules
deps/cutlass/CHANGELOG.md
deps/cutlass/CITATION.cff
deps/cutlass/CMakeLists.txt
deps/cutlass/CONTRIBUTORS.md
deps/cutlass/CUDA.cmake
deps/cutlass/Doxyfile
deps/cutlass/LICENSE.txt
deps/cutlass/PUBLICATIONS.md
deps/cutlass/README.md
deps/cutlass/bin2hex.cmake
deps/cutlass/cuBLAS.cmake
deps/cutlass/cuDNN.cmake
deps/cutlass/pyproject.toml
deps/cutlass/setup.cfg
deps/cutlass/cmake/CTestTestfile.configure.cmake
deps/cutlass/cmake/CTestTestfile.test.configure.cmake
deps/cutlass/cmake/NvidiaCutlassConfig.cmake.in
deps/cutlass/cmake/NvidiaCutlassPackageConfig.cmake
deps/cutlass/cmake/googletest.cmake
deps/cutlass/cmake/nop.cu
deps/cutlass/cmake/version_extended.h.in
deps/cutlass/include/cute/config.hpp
deps/cutlass/include/cute/int_tuple.hpp
deps/cutlass/include/cute/layout.hpp
deps/cutlass/include/cute/layout_composed.hpp
deps/cutlass/include/cute/pointer.hpp
deps/cutlass/include/cute/pointer_base.hpp
deps/cutlass/include/cute/pointer_flagged.hpp
deps/cutlass/include/cute/pointer_sparse.hpp
deps/cutlass/include/cute/pointer_swizzle.hpp
deps/cutlass/include/cute/stride.hpp
deps/cutlass/include/cute/swizzle.hpp
deps/cutlass/include/cute/swizzle_layout.hpp
deps/cutlass/include/cute/tensor.hpp
deps/cutlass/include/cute/tensor_impl.hpp
deps/cutlass/include/cute/tensor_predicate.hpp
deps/cutlass/include/cute/tensor_zip.hpp
deps/cutlass/include/cute/underscore.hpp
deps/cutlass/include/cute/algorithm/axpby.hpp
deps/cutlass/include/cute/algorithm/clear.hpp
deps/cutlass/include/cute/algorithm/cooperative_copy.hpp
deps/cutlass/include/cute/algorithm/cooperative_gemm.hpp
deps/cutlass/include/cute/algorithm/copy.hpp
deps/cutlass/include/cute/algorithm/fill.hpp
deps/cutlass/include/cute/algorithm/functional.hpp
deps/cutlass/include/cute/algorithm/gemm.hpp
deps/cutlass/include/cute/algorithm/prefer.hpp
python/mirage_project.egg-info/PKG-INFO
python/mirage_project.egg-info/SOURCES.txt
python/mirage_project.egg-info/dependency_links.txt
python/mirage_project.egg-info/not-zip-safe
python/mirage_project.egg-info/requires.txt
python/mirage_project.egg-info/top_level.txt
